{"success": true, "requestId": null, "resubmitToken": null, "msg": null, "code": 0, "content": {"pageNo": 1, "pageSize": 15, "hrInfoMap": {"5263219": {"phone": null, "userId": 621182, "receiveEmail": null, "realName": "HR", "portrait": "i/image/M00/27/1B/CgqKkVcl2o2AesUvAAAgV1EUAd4128.png", "positionName": "\u5e7f\u5dde\u660e\u52a8\u8f6f\u4ef6", "userLevel": "G1", "canTalk": true}, "4474090": {"phone": null, "userId": 1915295, "receiveEmail": null, "realName": "jiaoni.jiang", "portrait": null, "positionName": null, "userLevel": "G1", "canTalk": true}, "4935058": {"phone": null, "userId": 11379465, "receiveEmail": null, "realName": "\u90d1\u946b\u9896", "portrait": "i/image2/M01/73/44/CgotOVte2reAbqpkAAF7QuV9g7g459.jpg", "positionName": "\u6280\u672f\u9ad8\u7ea7\u7ecf\u7406", "userLevel": "G1", "canTalk": true}, "4826505": {"phone": null, "userId": 807140, "receiveEmail": null, "realName": "\u5355\u4e39\u4e39", "portrait": "i/image2/M01/67/4A/CgotOVtELBOAcvmuAADYpYtkmUI132.jpg", "positionName": "CEO", "userLevel": "G1", "canTalk": true}, "4935736": {"phone": null, "userId": 2425321, "receiveEmail": null, "realName": "\u4fe1\u7528\u7b97\u529b", "portrait": "i/image2/M01/6B/79/CgoB5ltNSsqAS0qOAABaowYdcQY67.jpeg", "positionName": "HR", "userLevel": "G1", "canTalk": true}, "4469663": {"phone": null, "userId": 6300350, "receiveEmail": null, "realName": "jianguowang", "portrait": "i/image2/M00/4C/E9/CgotOVr6sbCAeKGjAACgiK0FU5Y781.jpg", "positionName": "", "userLevel": "G1", "canTalk": true}, "1796145": {"phone": null, "userId": 3784157, "receiveEmail": null, "realName": "Musky", "portrait": "i/image2/M00/0E/93/CgoB5lnlih6AFVu3AAANuTPs_gE221.jpg", "positionName": "HR", "userLevel": "G1", "canTalk": true}, "5234706": {"phone": null, "userId": 1693120, "receiveEmail": null, "realName": "ydmhr", "portrait": null, "positionName": "\u4e3b\u7ba1", "userLevel": "G1", "canTalk": true}, "5290840": {"phone": null, "userId": 6695293, "receiveEmail": null, "realName": "yinshaohui", "portrait": "i/image3/M00/3D/B6/CgpOIFqwl5KALXoyAAcViX3t0cw314.png", "positionName": "", "userLevel": "G1", "canTalk": true}, "4914042": {"phone": null, "userId": 2231766, "receiveEmail": null, "realName": "brightwill", "portrait": null, "positionName": "\u62db\u8058\u4e3b\u7ba1", "userLevel": "G1", "canTalk": true}, "4437886": {"phone": null, "userId": 7684857, "receiveEmail": null, "realName": "\u6bd5\u7acb\u6885", "portrait": "i/image/M00/11/B1/CgpFT1j0S3OAIgyaAAV4X_Ovom0836.jpg", "positionName": "\u62db\u8058\u4e3b\u7ba1", "userLevel": "G1", "canTalk": true}, "4841507": {"phone": null, "userId": 8237, "receiveEmail": null, "realName": "justdoit", "portrait": "i/image3/M00/30/5F/Cgq2xlqh4iKACh5sAABu5sjkM4M234.png", "positionName": "HRBP", "userLevel": "G1", "canTalk": true}, "5247250": {"phone": null, "userId": 1305293, "receiveEmail": null, "realName": "Leon", "portrait": "i/image2/M01/AE/8A/CgoB5lv2RYqAaUxyAAACQ9rLjPI586.png", "positionName": "HR", "userLevel": "G1", "canTalk": true}, "5107023": {"phone": null, "userId": 8734468, "receiveEmail": null, "realName": "Stephen", "portrait": null, "positionName": "", "userLevel": "G1", "canTalk": true}, "3928841": {"phone": null, "userId": 8023287, "receiveEmail": null, "realName": "Teletraan HR", "portrait": "i/image2/M01/A9/1B/CgoB5lvo--KAYLnOAAMnhEr_DCI550.png", "positionName": "HR", "userLevel": "G1", "canTalk": true}}, "positionResult": {"totalCount": 437, "resultSize": 15, "hotLabels": null, "locationInfo": {"city": null, "district": null, "businessZone": null, "queryByGisCode": false, "locationCode": null, "isAllhotBusinessZone": false}, "queryAnalysisInfo": {"industryName": null, "usefulCompany": false, "companyName": null, "positionName": "\u81ea\u52a8\u5316\u6d4b\u8bd5\u5de5\u7a0b\u5e08", "jobNature": null}, "strategyProperty": {"name": "dm-csearch-useUserAllInterest", "id": 0}, "hiTags": null, "result": [{"city": "\u676d\u5dde", "createTime": "2018-11-30 13:41:24", "companyLogo": "i/image/M00/A3/94/CgqKkViqjdeAHATJAAAUWvQrzh0911.jpg", "industryField": "\u6e38\u620f,\u79fb\u52a8\u4e92\u8054\u7f51", "positionAdvantage": "\u798f\u5229\u597d\u3001\u53d1\u5c55\u7a7a\u95f4\u5927", "salary": "8k-15k", "companyId": 163852, "adWord": 0, "positionId": 5290840, "companySize": "150-500\u4eba", "approve": 1, "companyShortName": "\u6d6e\u4e91\u7f51\u7edc", "positionLables": ["\u4ea7\u54c1\u6d4b\u8bd5", "app\u6d4b\u8bd5"], "industryLables": [], "publisherId": 6695293, "financeStage": "\u4e0a\u5e02\u516c\u53f8", "companyLabelList": ["\u4e30\u539a\u5e74\u7ec8", "\u5b9a\u671f\u4f53\u68c0", "\u901a\u8baf\u6d25\u8d34", "\u5348\u9910\u8865\u52a9"], "district": "\u4e0b\u57ce\u533a", "businessZones": ["\u671d\u6656"], "score": 0, "positionName": "\u81ea\u52a8\u5316\u6d4b\u8bd5\u5de5\u7a0b\u5e08", "workYear": "1-3\u5e74", "education": "\u672c\u79d1", "jobNature": "\u5168\u804c", "companyFullName": "\u676d\u5dde\u6d6e\u4e91\u7f51\u7edc\u79d1\u6280\u6709\u9650\u516c\u53f8", "hitags": null, "resumeProcessRate": 63, "resumeProcessDay": 1, "imState": "disabled", "lastLogin": 1543737874000, "explain": null, "plus": null, "pcShow": 0, "appShow": 0, "deliver": 0, "gradeDescription": null, "promotionScoreExplain": null, "firstType": "\u5f00\u53d1|\u6d4b\u8bd5|\u8fd0\u7ef4\u7c7b", "secondType": "\u6d4b\u8bd5", "isSchoolJob": 0, "subwayline": "1\u53f7\u7ebf(\u4e0b\u6c99\u6c5f\u6ee8)", "stationname": "\u6c88\u5858\u6865", "linestaion": "1\u53f7\u7ebf(\u4e0b\u6c99\u6c5f\u6ee8)_\u897f\u6e56\u6587\u5316\u5e7f\u573a;1\u53f7\u7ebf(\u4e34\u5e73)_\u897f\u6e56\u6587\u5316\u5e7f\u573a;2\u53f7\u7ebf_\u6c88\u5858\u6865", "thirdType": "\u81ea\u52a8\u5316\u6d4b\u8bd5", "skillLables": ["\u4ea7\u54c1\u6d4b\u8bd5", "app\u6d4b\u8bd5"], "longitude": "120.159794", "latitude": "30.290304", "formatCreateTime": "2\u5929\u524d\u53d1\u5e03"}, {"city": "\u4e0a\u6d77", "createTime": "2018-12-01 13:20:51", "companyLogo": "image1/M00/00/05/Cgo8PFTUWAOACCV7AABgh9p1YEg115.jpg", "industryField": "\u79fb\u52a8\u4e92\u8054\u7f51,O2O", "positionAdvantage": "\u53d1\u5c55\u597d,\u798f\u5229\u597d,\u6c1b\u56f4\u597d,\u73af\u5883\u597d", "salary": "15k-30k", "companyId": 1291, "adWord": 0, "positionId": 4841507, "companySize": "500-2000\u4eba", "approve": 1, "companyShortName": "\u674f\u4ec1\u533b\u751f", "positionLables": [], "industryLables": [], "publisherId": 8237, "financeStage": "B\u8f6e", "companyLabelList": ["\u4e94\u9669\u4e00\u91d1", "\u5f39\u6027\u5de5\u4f5c", "\u5c97\u4f4d\u664b\u5347", "\u9876\u5c16\u56e2\u961f"], "district": "\u5f90\u6c47\u533a", "businessZones": ["\u6f15\u5b9d\u8def", "\u4e07\u6e90\u57ce", "\u4e1c\u5170\u8def"], "score": 0, "positionName": "\u81ea\u52a8\u5316\u6d4b\u8bd5\u5de5\u7a0b\u5e08", "workYear": "3-5\u5e74", "education": "\u672c\u79d1", "jobNature": "\u5168\u804c", "companyFullName": "\u7231\u6d77\u4f01\u4e1a\u7ba1\u7406\u54a8\u8be2\uff08\u4e0a\u6d77\uff09\u6709\u9650\u516c\u53f8", "hitags": null, "resumeProcessRate": 100, "resumeProcessDay": 1, "imState": "threeDays", "lastLogin": 1543641636000, "explain": null, "plus": null, "pcShow": 0, "appShow": 0, "deliver": 0, "gradeDescription": null, "promotionScoreExplain": null, "firstType": "\u5f00\u53d1|\u6d4b\u8bd5|\u8fd0\u7ef4\u7c7b", "secondType": "\u6d4b\u8bd5", "isSchoolJob": 0, "subwayline": null, "stationname": null, "linestaion": null, "thirdType": "\u6d4b\u8bd5\u5de5\u7a0b\u5e08", "skillLables": [], "longitude": "120.993464", "latitude": "30.994061", "formatCreateTime": "1\u5929\u524d\u53d1\u5e03"}, {"city": "\u5e7f\u5dde", "createTime": "2018-11-30 18:56:29", "companyLogo": "i/image/M00/2C/6B/Cgp3O1c5ZQ-AQgEyAABlrSMm-9A274.jpg", "industryField": "\u4f01\u4e1a\u670d\u52a1,\u6570\u636e\u670d\u52a1", "positionAdvantage": "\u6241\u5e73\u5316,\u6280\u672f\u63d0\u5347,\u5458\u5de5\u65c5\u6e38,\u4e94\u9669\u4e00\u91d1", "salary": "8k-12k", "companyId": 6558, "adWord": 0, "positionId": 5263219, "companySize": "150-500\u4eba", "approve": 1, "companyShortName": "\u660e\u52a8\u8f6f\u4ef6", "positionLables": ["Selenium"], "industryLables": [], "publisherId": 621182, "financeStage": "\u4e0a\u5e02\u516c\u53f8", "companyLabelList": ["\u6280\u80fd\u57f9\u8bad", "\u8282\u65e5\u793c\u7269", "\u5e74\u5e95\u53cc\u85aa", "\u7ee9\u6548\u5956\u91d1"], "district": "\u5929\u6cb3\u533a", "businessZones": ["\u5143\u5c97", "\u5c91\u6751", "\u9f99\u6d1e"], "score": 0, "positionName": "\u81ea\u52a8\u5316\u6d4b\u8bd5\u5de5\u7a0b\u5e08", "workYear": "1-3\u5e74", "education": "\u672c\u79d1", "jobNature": "\u5168\u804c", "companyFullName": "\u5e7f\u5dde\u660e\u52a8\u8f6f\u4ef6\u80a1\u4efd\u6709\u9650\u516c\u53f8", "hitags": null, "resumeProcessRate": 84, "resumeProcessDay": 1, "imState": "threeDays", "lastLogin": 1543571183000, "explain": null, "plus": null, "pcShow": 0, "appShow": 0, "deliver": 0, "gradeDescription": null, "promotionScoreExplain": null, "firstType": "\u5f00\u53d1|\u6d4b\u8bd5|\u8fd0\u7ef4\u7c7b", "secondType": "\u6d4b\u8bd5", "isSchoolJob": 0, "subwayline": "3\u53f7\u7ebf", "stationname": "\u957f\u6e74", "linestaion": "3\u53f7\u7ebf_\u5929\u6cb3\u5ba2\u8fd0\u7ad9;6\u53f7\u7ebf_\u957f\u6e74;6\u53f7\u7ebf_\u5929\u6cb3\u5ba2\u8fd0\u7ad9", "thirdType": "\u81ea\u52a8\u5316\u6d4b\u8bd5", "skillLables": ["Selenium"], "longitude": "113.350591", "latitude": "23.177721", "formatCreateTime": "2\u5929\u524d\u53d1\u5e03"}, {"city": "\u676d\u5dde", "createTime": "2018-12-01 23:10:06", "companyLogo": "i/image/M00/33/82/CgpFT1lA0PWAJmDhAABrwy5isHE899.png", "industryField": "\u6570\u636e\u670d\u52a1,\u4f01\u4e1a\u670d\u52a1", "positionAdvantage": "\u4e94\u9669\u4e00\u91d1,\u6280\u672f\u6c1b\u56f4\u597d,\u53d1\u5c55\u7a7a\u95f4\u5927,\u5f39\u6027\u5de5\u4f5c\u5236", "salary": "10k-20k", "companyId": 211574, "adWord": 0, "positionId": 3928841, "companySize": "15-50\u4eba", "approve": 1, "companyShortName": "TELETRAAN", "positionLables": ["\u811a\u672c"], "industryLables": [], "publisherId": 8023287, "financeStage": "\u5929\u4f7f\u8f6e", "companyLabelList": ["\u5168\u65b0MAC", "24+\u663e\u793a\u5668", "\u7845\u8c37\u5de5\u4f5c\u673a\u4f1a", "\u80a1\u7968\u671f\u6743"], "district": "\u6ee8\u6c5f\u533a", "businessZones": ["\u897f\u5174"], "score": 0, "positionName": "\u81ea\u52a8\u5316\u6d4b\u8bd5\u5de5\u7a0b\u5e08", "workYear": "3-5\u5e74", "education": "\u672c\u79d1", "jobNature": "\u5168\u804c", "companyFullName": "\u6d59\u6c5f\u5929\u5782\u79d1\u6280\u6709\u9650\u516c\u53f8", "hitags": null, "resumeProcessRate": 77, "resumeProcessDay": 2, "imState": "disabled", "lastLogin": 1543677153000, "explain": null, "plus": null, "pcShow": 0, "appShow": 0, "deliver": 0, "gradeDescription": null, "promotionScoreExplain": null, "firstType": "\u5f00\u53d1|\u6d4b\u8bd5|\u8fd0\u7ef4\u7c7b", "secondType": "\u6d4b\u8bd5", "isSchoolJob": 0, "subwayline": "1\u53f7\u7ebf(\u4e0b\u6c99\u6c5f\u6ee8)", "stationname": "\u6c5f\u9675\u8def", "linestaion": "1\u53f7\u7ebf(\u4e0b\u6c99\u6c5f\u6ee8)_\u6ee8\u548c\u8def;1\u53f7\u7ebf(\u4e0b\u6c99\u6c5f\u6ee8)_\u6c5f\u9675\u8def;1\u53f7\u7ebf(\u4e34\u5e73)_\u6ee8\u548c\u8def;1\u53f7\u7ebf(\u4e34\u5e73)_\u6c5f\u9675\u8def", "thirdType": "\u81ea\u52a8\u5316\u6d4b\u8bd5", "skillLables": ["\u811a\u672c"], "longitude": "120.211816", "latitude": "30.20856", "formatCreateTime": "1\u5929\u524d\u53d1\u5e03"}, {"city": "\u5317\u4eac", "createTime": "2018-11-30 16:41:37", "companyLogo": "image1/M00/00/08/Cgo8PFTUWA-AdaTRAAA79zuDOBc464.jpg", "industryField": "\u6570\u636e\u670d\u52a1,\u4f01\u4e1a\u670d\u52a1", "positionAdvantage": "\u5927\u6570\u636e,\u4e0a\u5e02\u516c\u53f8,\u798f\u5229\u597d,\u6210\u957f\u7a7a\u95f4\u5927", "salary": "15k-25k", "companyId": 3038, "adWord": 0, "positionId": 4437886, "companySize": "500-2000\u4eba", "approve": 1, "companyShortName": "Gridsum \u56fd\u53cc", "positionLables": ["\u4fe1\u606f\u5b89\u5168", "\u5927\u6570\u636e", "Loadrunner", "\u6027\u80fd\u6d4b\u8bd5"], "industryLables": ["\u4fe1\u606f\u5b89\u5168", "\u5927\u6570\u636e", "Loadrunner", "\u6027\u80fd\u6d4b\u8bd5"], "publisherId": 7684857, "financeStage": "\u4e0a\u5e02\u516c\u53f8", "companyLabelList": ["\u5e74\u5ea6\u65c5\u6e38", "\u8282\u65e5\u793c\u7269", "\u5e74\u5e95\u53cc\u85aa", "\u5e26\u85aa\u5e74\u5047"], "district": "\u6d77\u6dc0\u533a", "businessZones": ["\u4e2d\u5173\u6751", "\u77e5\u6625\u8def", "\u53cc\u6986\u6811"], "score": 0, "positionName": "\u81ea\u52a8\u5316\u6d4b\u8bd5\u5de5\u7a0b\u5e08", "workYear": "3-5\u5e74", "education": "\u672c\u79d1", "jobNature": "\u5168\u804c", "companyFullName": "\u5317\u4eac\u56fd\u53cc\u79d1\u6280\u6709\u9650\u516c\u53f8", "hitags": ["\u8d2d\u4e70\u793e\u4fdd", "\u8bd5\u7528\u671f\u4e0a\u793e\u4fdd", "\u514d\u8d39\u4f11\u95f2\u6e38", "\u8bd5\u7528\u671f\u4e0a\u516c\u79ef\u91d1", "\u514d\u8d39\u5065\u8eab\u623f", "\u521b\u65b0\u4eba\u624d\u652f\u6301", "\u514d\u8d39\u4f53\u68c0", "\u6bcf\u6708\u9910\u8865", "6\u96691\u91d1"], "resumeProcessRate": 35, "resumeProcessDay": 1, "imState": "disabled", "lastLogin": 1543565402000, "explain": null, "plus": null, "pcShow": 0, "appShow": 0, "deliver": 0, "gradeDescription": null, "promotionScoreExplain": null, "firstType": "\u5f00\u53d1|\u6d4b\u8bd5|\u8fd0\u7ef4\u7c7b", "secondType": "\u6d4b\u8bd5", "isSchoolJob": 0, "subwayline": "10\u53f7\u7ebf", "stationname": "\u77e5\u6625\u8def", "linestaion": "4\u53f7\u7ebf\u5927\u5174\u7ebf_\u4eba\u6c11\u5927\u5b66;4\u53f7\u7ebf\u5927\u5174\u7ebf_\u6d77\u6dc0\u9ec4\u5e84;10\u53f7\u7ebf_\u6d77\u6dc0\u9ec4\u5e84;10\u53f7\u7ebf_\u77e5\u6625\u91cc;10\u53f7\u7ebf_\u77e5\u6625\u8def;13\u53f7\u7ebf_\u77e5\u6625\u8def", "thirdType": "\u81ea\u52a8\u5316\u6d4b\u8bd5", "skillLables": ["Loadrunner", "\u6027\u80fd\u6d4b\u8bd5"], "longitude": "116.33175", "latitude": "39.975987", "formatCreateTime": "2\u5929\u524d\u53d1\u5e03"}, {"city": "\u4e0a\u6d77", "createTime": "2018-11-30 14:58:13", "companyLogo": "i/image2/M01/6B/07/CgotOVtMTvqAG0MeAAA3BQt3aAM696.png", "industryField": "\u79fb\u52a8\u4e92\u8054\u7f51,\u91d1\u878d", "positionAdvantage": "\u5e74\u7ec8\u5956\u4e30\u539a,\u5f39\u6027\u5de5\u4f5c,\u5347\u804c\u52a0\u85aa,\u6c1b\u56f4\u6b22\u5feb", "salary": "15k-25k", "companyId": 93141, "adWord": 0, "positionId": 4935736, "companySize": "150-500\u4eba", "approve": 1, "companyShortName": "\u4fe1\u7528\u7b97\u529b", "positionLables": [], "industryLables": [], "publisherId": 2425321, "financeStage": "B\u8f6e", "companyLabelList": ["\u5e74\u5e95\u53cc\u85aa", "\u80a1\u7968\u671f\u6743", "\u5e26\u85aa\u5e74\u5047", "\u7ee9\u6548\u5956\u91d1"], "district": "\u6768\u6d66\u533a", "businessZones": null, "score": 0, "positionName": "\u81ea\u52a8\u5316\u6d4b\u8bd5\u5de5\u7a0b\u5e08", "workYear": "5-10\u5e74", "education": "\u672c\u79d1", "jobNature": "\u5168\u804c", "companyFullName": "\u946b\u6d8c\u7b97\u529b\u4fe1\u606f\u79d1\u6280\uff08\u4e0a\u6d77\uff09\u6709\u9650\u516c\u53f8", "hitags": null, "resumeProcessRate": 100, "resumeProcessDay": 1, "imState": "threeDays", "lastLogin": 1543561061000, "explain": null, "plus": null, "pcShow": 0, "appShow": 0, "deliver": 0, "gradeDescription": null, "promotionScoreExplain": null, "firstType": "\u5f00\u53d1|\u6d4b\u8bd5|\u8fd0\u7ef4\u7c7b", "secondType": "\u6d4b\u8bd5", "isSchoolJob": 0, "subwayline": "10\u53f7\u7ebf(\u822a\u4e2d\u8def)", "stationname": "\u4e94\u89d2\u573a", "linestaion": "8\u53f7\u7ebf_\u7fd4\u6bb7\u8def;10\u53f7\u7ebf(\u822a\u4e2d\u8def)_\u6c5f\u6e7e\u4f53\u80b2\u573a;10\u53f7\u7ebf(\u822a\u4e2d\u8def)_\u4e94\u89d2\u573a;10\u53f7\u7ebf(\u822a\u4e2d\u8def)_\u56fd\u6743\u8def;10\u53f7\u7ebf(\u8679\u6865\u706b\u8f66\u7ad9)_\u6c5f\u6e7e\u4f53\u80b2\u573a;10\u53f7\u7ebf(\u8679\u6865\u706b\u8f66\u7ad9)_\u4e94\u89d2\u573a;10\u53f7\u7ebf(\u8679\u6865\u706b\u8f66\u7ad9)_\u56fd\u6743\u8def", "thirdType": "\u81ea\u52a8\u5316\u6d4b\u8bd5", "skillLables": [], "longitude": "121.5181", "latitude": "31.300344", "formatCreateTime": "2\u5929\u524d\u53d1\u5e03"}, {"city": "\u5317\u4eac", "createTime": "2018-11-30 18:28:18", "companyLogo": "i/image2/M00/4E/6C/CgoB5lsGXsmALIoZAABi1lDHEyw779.jpg", "industryField": "O2O", "positionAdvantage": "\u4e03\u9669\u4e00\u91d1,\u7ee9\u6548\u5956\u91d1,\u5e74\u5e95\u53cc\u85aa,\u8282\u65e5\u798f\u5229\u7b49", "salary": "10k-20k", "companyId": 48133, "adWord": 0, "positionId": 4826505, "companySize": "500-2000\u4eba", "approve": 1, "companyShortName": "\u798f\u4f51\u5361\u8f66", "positionLables": ["\u529f\u80fd\u6d4b\u8bd5"], "industryLables": [], "publisherId": 807140, "financeStage": "C\u8f6e", "companyLabelList": ["\u8282\u65e5\u793c\u7269", "\u5e74\u5e95\u53cc\u85aa", "\u5b9a\u671f\u4f53\u68c0", "\u4e03\u9669\u4e00\u91d1"], "district": "\u6d77\u6dc0\u533a", "businessZones": ["\u897f\u5317\u65fa", "\u4e0a\u5730", "\u9a6c\u8fde\u6d3c"], "score": 0, "positionName": "\u81ea\u52a8\u5316\u6d4b\u8bd5\u5de5\u7a0b\u5e08", "workYear": "3-5\u5e74", "education": "\u672c\u79d1", "jobNature": "\u5168\u804c", "companyFullName": "\u5317\u4eac\u798f\u4f51\u591a\u591a\u4fe1\u606f\u6280\u672f\u6709\u9650\u516c\u53f8", "hitags": null, "resumeProcessRate": 100, "resumeProcessDay": 1, "imState": "threeDays", "lastLogin": 1543557419000, "explain": null, "plus": null, "pcShow": 0, "appShow": 0, "deliver": 0, "gradeDescription": null, "promotionScoreExplain": null, "firstType": "\u5f00\u53d1|\u6d4b\u8bd5|\u8fd0\u7ef4\u7c7b", "secondType": "\u6d4b\u8bd5", "isSchoolJob": 0, "subwayline": "13\u53f7\u7ebf", "stationname": "\u4e0a\u5730", "linestaion": "13\u53f7\u7ebf_\u4e0a\u5730", "thirdType": "\u6d4b\u8bd5\u5de5\u7a0b\u5e08", "skillLables": ["\u529f\u80fd\u6d4b\u8bd5"], "longitude": "116.307278", "latitude": "40.035928", "formatCreateTime": "2\u5929\u524d\u53d1\u5e03"}, {"city": "\u6210\u90fd", "createTime": "2018-11-30 09:52:24", "companyLogo": "i/image2/M01/A3/14/CgotOVvYI_CAVrCFAAAaUSx2tYg486.png", "industryField": "\u79fb\u52a8\u4e92\u8054\u7f51", "positionAdvantage": "\u81ea\u52a8\u5316\u67b6\u6784,\u4e92\u8054\u7f51\u4ea7\u54c1,\u5f39\u6027\u5de5\u4f5c", "salary": "10k-20k", "companyId": 29303, "adWord": 0, "positionId": 4474090, "companySize": "500-2000\u4eba", "approve": 1, "companyShortName": "\u6d3b\u8dc3\u7f51\u7edc", "positionLables": [], "industryLables": [], "publisherId": 1915295, "financeStage": "\u4e0a\u5e02\u516c\u53f8", "companyLabelList": ["\u4e94\u9669\u4e00\u91d1", "\u5f39\u6027\u5de5\u4f5c", "\u5b9a\u671f\u4f53\u68c0", "\u8865\u5145\u533b\u7597"], "district": "\u9526\u6c5f\u533a", "businessZones": ["\u7ea2\u661f\u8def", "\u4e1c\u95e8\u5927\u6865", "\u6625\u7199\u8def"], "score": 0, "positionName": "\u81ea\u52a8\u5316\u6d4b\u8bd5\u5de5\u7a0b\u5e08", "workYear": "3-5\u5e74", "education": "\u672c\u79d1", "jobNature": "\u5168\u804c", "companyFullName": "\u6d3b\u8dc3\u7f51\u7edc\uff08\u6210\u90fd\uff09\u6709\u9650\u516c\u53f8", "hitags": null, "resumeProcessRate": 100, "resumeProcessDay": 1, "imState": "threeDays", "lastLogin": 1543542765000, "explain": null, "plus": null, "pcShow": 0, "appShow": 0, "deliver": 0, "gradeDescription": null, "promotionScoreExplain": null, "firstType": "\u5f00\u53d1|\u6d4b\u8bd5|\u8fd0\u7ef4\u7c7b", "secondType": "\u6d4b\u8bd5", "isSchoolJob": 0, "subwayline": null, "stationname": null, "linestaion": null, "thirdType": "\u81ea\u52a8\u5316\u6d4b\u8bd5", "skillLables": [], "longitude": "103.99341", "latitude": "30.994233", "formatCreateTime": "2\u5929\u524d\u53d1\u5e03"}, {"city": "\u4e0a\u6d77", "createTime": "2018-11-30 09:28:55", "companyLogo": "i/image3/M00/3F/A2/CgpOIFqyLtWAIKr3AAA5XxrO2es309.png", "industryField": "\u79fb\u52a8\u4e92\u8054\u7f51", "positionAdvantage": "B\u8f6e,\u79fb\u52a8\u4e92\u8054\u7f51,\u6280\u672f\u6c1b\u56f4\u6d53,\u8d85\u957f\u5e74\u5047", "salary": "10k-20k", "companyId": 154561, "adWord": 0, "positionId": 5107023, "companySize": "50-150\u4eba", "approve": 1, "companyShortName": "MoSeeker\u4edf\u5bfb", "positionLables": ["Selenium", "Jmeter"], "industryLables": [], "publisherId": 8734468, "financeStage": "B\u8f6e", "companyLabelList": ["\u5e26\u85aa\u5e74\u5047", "\u5b9a\u671f\u4f53\u68c0", "\u5e74\u7ec8\u5206\u7ea2", "\u8282\u65e5\u793c\u7269"], "district": "\u5f90\u6c47\u533a", "businessZones": null, "score": 0, "positionName": "\u81ea\u52a8\u5316\u6d4b\u8bd5\u5de5\u7a0b\u5e08", "workYear": "3-5\u5e74", "education": "\u672c\u79d1", "jobNature": "\u5168\u804c", "companyFullName": "\u4e0a\u6d77\u5927\u5c82\u7f51\u7edc\u79d1\u6280\u6709\u9650\u516c\u53f8", "hitags": null, "resumeProcessRate": 100, "resumeProcessDay": 1, "imState": "threeDays", "lastLogin": 1543568979000, "explain": null, "plus": null, "pcShow": 0, "appShow": 0, "deliver": 0, "gradeDescription": null, "promotionScoreExplain": null, "firstType": "\u5f00\u53d1|\u6d4b\u8bd5|\u8fd0\u7ef4\u7c7b", "secondType": "\u6d4b\u8bd5", "isSchoolJob": 0, "subwayline": "11\u53f7\u7ebf(\u82b1\u6865)", "stationname": "\u8679\u6865\u8def", "linestaion": "1\u53f7\u7ebf_\u5f90\u5bb6\u6c47;3\u53f7\u7ebf_\u8679\u6865\u8def;3\u53f7\u7ebf_\u5b9c\u5c71\u8def;4\u53f7\u7ebf_\u8679\u6865\u8def;9\u53f7\u7ebf_\u5f90\u5bb6\u6c47;9\u53f7\u7ebf_\u5b9c\u5c71\u8def;10\u53f7\u7ebf(\u822a\u4e2d\u8def)_\u4ea4\u901a\u5927\u5b66;10\u53f7\u7ebf(\u822a\u4e2d\u8def)_\u8679\u6865\u8def;10\u53f7\u7ebf(\u8679\u6865\u706b\u8f66\u7ad9)_\u4ea4\u901a\u5927\u5b66;10\u53f7\u7ebf(\u8679\u6865\u706b\u8f66\u7ad9)_\u8679\u6865\u8def;11\u53f7\u7ebf(\u5609\u5b9a\u5317)_\u5f90\u5bb6\u6c47;11\u53f7\u7ebf(\u5609\u5b9a\u5317)_\u4ea4\u901a\u5927\u5b66;11\u53f7\u7ebf(\u82b1\u6865)_\u5f90\u5bb6\u6c47;11\u53f7\u7ebf(\u82b1\u6865)_\u4ea4\u901a\u5927\u5b66", "thirdType": "\u81ea\u52a8\u5316\u6d4b\u8bd5", "skillLables": ["Selenium", "Jmeter"], "longitude": "121.432441", "latitude": "31.196247", "formatCreateTime": "2\u5929\u524d\u53d1\u5e03"}, {"city": "\u6210\u90fd", "createTime": "2018-11-30 14:50:08", "companyLogo": "i/image2/M01/A0/4E/CgoB5lvRWOCAbnW9AAAKddl7lKc910.jpg", "industryField": "\u91d1\u878d,\u533a\u5757\u94fe", "positionAdvantage": "\u91d1\u878d\u79d1\u6280,\u4e94\u9669\u4e00\u91d1,\u6c1b\u56f4\u524d\u666f\u597d,\u505a\u4e94\u4f11\u4e8c", "salary": "6k-12k", "companyId": 51814, "adWord": 0, "positionId": 5247250, "companySize": "15-50\u4eba", "approve": 1, "companyShortName": "\u6e90\u8681\u79d1\u6280 RootAnt", "positionLables": ["\u79fb\u52a8\u4e92\u8054\u7f51", "\u91d1\u878d", "\u6027\u80fd\u6d4b\u8bd5"], "industryLables": ["\u79fb\u52a8\u4e92\u8054\u7f51", "\u91d1\u878d", "\u6027\u80fd\u6d4b\u8bd5"], "publisherId": 1305293, "financeStage": "\u5929\u4f7f\u8f6e", "companyLabelList": ["\u5e74\u5e95\u53cc\u85aa", "\u8282\u65e5\u793c\u7269", "\u6280\u80fd\u57f9\u8bad", "\u7ee9\u6548\u5956\u91d1"], "district": "\u9ad8\u65b0\u533a", "businessZones": null, "score": 0, "positionName": "\u81ea\u52a8\u5316\u6d4b\u8bd5\u5de5\u7a0b\u5e08", "workYear": "\u4e0d\u9650", "education": "\u672c\u79d1", "jobNature": "\u5168\u804c", "companyFullName": "\u4e0a\u6d77\u6e90\u8681\u4fe1\u606f\u79d1\u6280\u6709\u9650\u516c\u53f8", "hitags": null, "resumeProcessRate": 86, "resumeProcessDay": 1, "imState": "threeDays", "lastLogin": 1543571064000, "explain": null, "plus": null, "pcShow": 0, "appShow": 0, "deliver": 0, "gradeDescription": null, "promotionScoreExplain": null, "firstType": "\u5f00\u53d1|\u6d4b\u8bd5|\u8fd0\u7ef4\u7c7b", "secondType": "\u6d4b\u8bd5", "isSchoolJob": 0, "subwayline": "1\u53f7\u7ebf", "stationname": "\u5b75\u5316\u56ed", "linestaion": "1\u53f7\u7ebf_\u5b75\u5316\u56ed;1\u53f7\u7ebf_\u91d1\u878d\u57ce;1\u53f7\u7ebf_\u9ad8\u65b0", "thirdType": "\u81ea\u52a8\u5316\u6d4b\u8bd5", "skillLables": ["\u6027\u80fd\u6d4b\u8bd5"], "longitude": "104.055144", "latitude": "30.586356", "formatCreateTime": "2\u5929\u524d\u53d1\u5e03"}, {"city": "\u897f\u5b89", "createTime": "2018-11-30 11:58:38", "companyLogo": "i/image/M00/17/2B/CgqKkVbxBsGAS4I4AAANwQ6dVys338.jpg", "industryField": "O2O,\u5176\u4ed6", "positionAdvantage": "\u6709\u673a\u4f1a\u8d74\u7f8e\u56fd\u51fa\u5dee\u3001\u8fdb\u4fee\u3001\u957f\u671f\u5de5\u4f5c", "salary": "8k-11k", "companyId": 118198, "adWord": 0, "positionId": 1796145, "companySize": "50-150\u4eba", "approve": 1, "companyShortName": "\u897f\u5b89\u5353\u6d3e\u4fe1\u606f\u79d1\u6280\u6709\u9650\u516c\u53f8", "positionLables": [], "industryLables": [], "publisherId": 3784157, "financeStage": "B\u8f6e", "companyLabelList": ["\u5e74\u5e95\u53cc\u85aa", "\u4ea4\u901a\u8865\u52a9", "\u5e26\u85aa\u5e74\u5047", "\u8282\u65e5\u793c\u7269"], "district": "\u9ad8\u65b0\u6280\u672f\u4ea7\u4e1a\u5f00\u53d1\u533a", "businessZones": ["\u6ca3\u60e0\u5357\u8def", "\u5510\u5ef6\u8def", "\u65fa\u5ea7\u73b0\u4ee3\u57ce", "\u6ca3\u60e0\u5357\u8def", "\u5510\u5ef6\u8def", "\u65fa\u5ea7\u73b0\u4ee3\u57ce"], "score": 0, "positionName": "\u81ea\u52a8\u5316\u6d4b\u8bd5\u5de5\u7a0b\u5e08", "workYear": "1-3\u5e74", "education": "\u4e0d\u9650", "jobNature": "\u5168\u804c", "companyFullName": "\u897f\u5b89\u5353\u6d3e\u4fe1\u606f\u79d1\u6280\u6709\u9650\u516c\u53f8", "hitags": null, "resumeProcessRate": 100, "resumeProcessDay": 1, "imState": "today", "lastLogin": 1543659445000, "explain": null, "plus": null, "pcShow": 0, "appShow": 0, "deliver": 0, "gradeDescription": null, "promotionScoreExplain": null, "firstType": "\u5f00\u53d1|\u6d4b\u8bd5|\u8fd0\u7ef4\u7c7b", "secondType": "\u6d4b\u8bd5", "isSchoolJob": 0, "subwayline": null, "stationname": null, "linestaion": null, "thirdType": "\u5176\u4ed6\u6d4b\u8bd5", "skillLables": [], "longitude": "108.88432979", "latitude": "34.21327988", "formatCreateTime": "2\u5929\u524d\u53d1\u5e03"}, {"city": "\u4e0a\u6d77", "createTime": "2018-11-30 09:59:49", "companyLogo": "i/image/M00/72/00/Cgp3O1grutOAVSLRAAAkJReBGpA082.png", "industryField": "\u79fb\u52a8\u4e92\u8054\u7f51,\u91d1\u878d", "positionAdvantage": "\u6d4b\u8bd5\u5de5\u7a0b\u5e08", "salary": "15k-18k", "companyId": 157588, "adWord": 0, "positionId": 4469663, "companySize": "50-150\u4eba", "approve": 1, "companyShortName": "\u88d5\u5b81\u79d1\u6280", "positionLables": ["\u811a\u672c"], "industryLables": [], "publisherId": 6300350, "financeStage": "\u672a\u878d\u8d44", "companyLabelList": [], "district": "\u666e\u9640\u533a", "businessZones": null, "score": 0, "positionName": "\u81ea\u52a8\u5316\u6d4b\u8bd5\u5de5\u7a0b\u5e08", "workYear": "5-10\u5e74", "education": "\u672c\u79d1", "jobNature": "\u5168\u804c", "companyFullName": "\u4e0a\u6d77\u88d5\u5b81\u4fe1\u606f\u79d1\u6280\u6709\u9650\u516c\u53f8", "hitags": null, "resumeProcessRate": 83, "resumeProcessDay": 1, "imState": "threeDays", "lastLogin": 1543543355000, "explain": null, "plus": null, "pcShow": 0, "appShow": 0, "deliver": 0, "gradeDescription": null, "promotionScoreExplain": null, "firstType": "\u5f00\u53d1|\u6d4b\u8bd5|\u8fd0\u7ef4\u7c7b", "secondType": "\u6d4b\u8bd5", "isSchoolJob": 0, "subwayline": "11\u53f7\u7ebf(\u82b1\u6865)", "stationname": "\u6b66\u5b81\u8def", "linestaion": "2\u53f7\u7ebf_\u6c5f\u82cf\u8def;3\u53f7\u7ebf_\u66f9\u6768\u8def;3\u53f7\u7ebf_\u91d1\u6c99\u6c5f\u8def;4\u53f7\u7ebf_\u91d1\u6c99\u6c5f\u8def;4\u53f7\u7ebf_\u66f9\u6768\u8def;7\u53f7\u7ebf_\u660c\u5e73\u8def;7\u53f7\u7ebf_\u957f\u5bff\u8def;11\u53f7\u7ebf(\u5609\u5b9a\u5317)_\u6c5f\u82cf\u8def;11\u53f7\u7ebf(\u5609\u5b9a\u5317)_\u9686\u5fb7\u8def;11\u53f7\u7ebf(\u5609\u5b9a\u5317)_\u66f9\u6768\u8def;11\u53f7\u7ebf(\u82b1\u6865)_\u6c5f\u82cf\u8def;11\u53f7\u7ebf(\u82b1\u6865)_\u9686\u5fb7\u8def;11\u53f7\u7ebf(\u82b1\u6865)_\u66f9\u6768\u8def;13\u53f7\u7ebf_\u91d1\u6c99\u6c5f\u8def;13\u53f7\u7ebf_\u9686\u5fb7\u8def;13\u53f7\u7ebf_\u6b66\u5b81\u8def;13\u53f7\u7ebf_\u957f\u5bff\u8def", "thirdType": "\u6d4b\u8bd5\u5de5\u7a0b\u5e08", "skillLables": ["\u811a\u672c"], "longitude": "121.428005", "latitude": "31.230902", "formatCreateTime": "2\u5929\u524d\u53d1\u5e03"}, {"city": "\u6df1\u5733", "createTime": "2018-11-30 13:42:00", "companyLogo": "image1/M00/26/8D/Cgo8PFVVwA6AAQoIAACpLomPZUc821.jpg", "industryField": "\u79fb\u52a8\u4e92\u8054\u7f51,\u7535\u5b50\u5546\u52a1", "positionAdvantage": "\u4e94\u9669\u4e00\u91d1,\u5468\u672b\u53cc\u4f11,\u6241\u5e73\u5316\u7ba1\u7406,\u5f39\u6027\u65f6\u95f4", "salary": "10k-20k", "companyId": 70037, "adWord": 0, "positionId": 5234706, "companySize": "150-500\u4eba", "approve": 1, "companyShortName": "\u5f15\u5bfc\u7f8e", "positionLables": ["\u811a\u672c"], "industryLables": [], "publisherId": 1693120, "financeStage": "A\u8f6e", "companyLabelList": ["\u5e74\u5e95\u53cc\u85aa", "\u7ee9\u6548\u5956\u91d1", "\u5c97\u4f4d\u664b\u5347", "\u5e26\u85aa\u5e74\u5047"], "district": "\u798f\u7530\u533a", "businessZones": null, "score": 0, "positionName": "\u81ea\u52a8\u5316\u6d4b\u8bd5\u5de5\u7a0b\u5e08", "workYear": "3-5\u5e74", "education": "\u672c\u79d1", "jobNature": "\u5168\u804c", "companyFullName": "\u6df1\u5733\u5e02\u5f15\u5bfc\u7f8e\u7535\u5b50\u5546\u52a1\u6709\u9650\u516c\u53f8", "hitags": null, "resumeProcessRate": 10, "resumeProcessDay": 1, "imState": "threeDays", "lastLogin": 1543547930000, "explain": null, "plus": null, "pcShow": 0, "appShow": 0, "deliver": 0, "gradeDescription": null, "promotionScoreExplain": null, "firstType": "\u5f00\u53d1|\u6d4b\u8bd5|\u8fd0\u7ef4\u7c7b", "secondType": "\u6d4b\u8bd5", "isSchoolJob": 0, "subwayline": "7\u53f7\u7ebf", "stationname": "\u519c\u6797", "linestaion": "1\u53f7\u7ebf/\u7f57\u5b9d\u7ebf_\u7af9\u5b50\u6797;1\u53f7\u7ebf/\u7f57\u5b9d\u7ebf_\u4fa8\u57ce\u4e1c;7\u53f7\u7ebf_\u519c\u6797", "thirdType": "\u81ea\u52a8\u5316\u6d4b\u8bd5", "skillLables": ["\u811a\u672c"], "longitude": "114.005995", "latitude": "22.533954", "formatCreateTime": "2\u5929\u524d\u53d1\u5e03"}, {"city": "\u5317\u4eac", "createTime": "2018-11-30 13:44:06", "companyLogo": "i/image2/M01/73/0B/CgotOVteqFOAMtTrAACBrnYWk4E769.jpg", "industryField": "\u79fb\u52a8\u4e92\u8054\u7f51", "positionAdvantage": "\u963f\u91cc\u56e2\u961f,\u6280\u672f\u5927\u725b,\u65b0\u96f6\u552e\u524d\u6cbf,\u5f15\u9886\u6f6e\u6d41", "salary": "15k-30k", "companyId": 27633, "adWord": 0, "positionId": 4935058, "companySize": "2000\u4eba\u4ee5\u4e0a", "approve": 1, "companyShortName": "\u94f6\u6cf0\u5546\u4e1a\u96c6\u56e2", "positionLables": ["\u7535\u5546", "\u65b0\u96f6\u552e", "\u6d4b\u8bd5\u5f00\u53d1", "\u811a\u672c"], "industryLables": ["\u7535\u5546", "\u65b0\u96f6\u552e", "\u6d4b\u8bd5\u5f00\u53d1", "\u811a\u672c"], "publisherId": 11379465, "financeStage": "\u4e0d\u9700\u8981\u878d\u8d44", "companyLabelList": ["\u901a\u8baf\u6d25\u8d34", "\u5c97\u4f4d\u664b\u5347", "\u6280\u80fd\u57f9\u8bad", "\u7ba1\u7406\u89c4\u8303"], "district": "\u671d\u9633\u533a", "businessZones": ["\u56db\u60e0", "\u5927\u671b\u8def", "\u9ad8\u7891\u5e97"], "score": 0, "positionName": "\u81ea\u52a8\u5316\u6d4b\u8bd5\u5de5\u7a0b\u5e08", "workYear": "3-5\u5e74", "education": "\u672c\u79d1", "jobNature": "\u5168\u804c", "companyFullName": "\u6d59\u6c5f\u94f6\u6cf0\u767e\u8d27\u6709\u9650\u516c\u53f8", "hitags": null, "resumeProcessRate": 100, "resumeProcessDay": 2, "imState": "threeDays", "lastLogin": 1543564884000, "explain": null, "plus": null, "pcShow": 0, "appShow": 0, "deliver": 0, "gradeDescription": null, "promotionScoreExplain": null, "firstType": "\u5f00\u53d1|\u6d4b\u8bd5|\u8fd0\u7ef4\u7c7b", "secondType": "\u6d4b\u8bd5", "isSchoolJob": 0, "subwayline": "\u516b\u901a\u7ebf", "stationname": "\u56db\u60e0\u4e1c", "linestaion": "1\u53f7\u7ebf_\u56db\u60e0;1\u53f7\u7ebf_\u56db\u60e0\u4e1c;\u516b\u901a\u7ebf_\u56db\u60e0\u4e1c", "thirdType": "\u6d4b\u8bd5\u5f00\u53d1", "skillLables": ["\u6d4b\u8bd5\u5f00\u53d1", "\u811a\u672c"], "longitude": "116.508075", "latitude": "39.905111", "formatCreateTime": "2\u5929\u524d\u53d1\u5e03"}, {"city": "\u53a6\u95e8", "createTime": "2018-11-30 09:40:00", "companyLogo": "i/image2/M00/2B/6F/CgotOVossQSALX0mAAAX4NW1kBI517.jpg", "industryField": "\u79fb\u52a8\u4e92\u8054\u7f51,\u4f01\u4e1a\u670d\u52a1", "positionAdvantage": "\u56e2\u961fnic,\u6280\u672f\u5927\u725b,\u6280\u672f\u4ea4\u6d41,\u5f39\u6027\u5de5\u4f5c", "salary": "8k-15k", "companyId": 87170, "adWord": 0, "positionId": 4914042, "companySize": "150-500\u4eba", "approve": 1, "companyShortName": "\u51c6\u52a8\u7f51\u7edc\u79d1\u6280", "positionLables": [], "industryLables": [], "publisherId": 2231766, "financeStage": "B\u8f6e", "companyLabelList": ["\u7cbe\u82f1\u56e2\u961f", "\u6241\u5e73\u7ba1\u7406", "\u81ea\u7531\u5f00\u653e", "\u6280\u672f\u5927\u725b"], "district": "\u601d\u660e\u533a", "businessZones": null, "score": 0, "positionName": "\u81ea\u52a8\u5316\u6d4b\u8bd5\u5de5\u7a0b\u5e08", "workYear": "3-5\u5e74", "education": "\u5927\u4e13", "jobNature": "\u5168\u804c", "companyFullName": "\u51c6\u52a8\u7f51\u7edc\u79d1\u6280(\u53a6\u95e8)\u6709\u9650\u516c\u53f8", "hitags": null, "resumeProcessRate": 28, "resumeProcessDay": 2, "imState": "disabled", "lastLogin": 1543568650000, "explain": null, "plus": null, "pcShow": 0, "appShow": 0, "deliver": 0, "gradeDescription": null, "promotionScoreExplain": null, "firstType": "\u5f00\u53d1|\u6d4b\u8bd5|\u8fd0\u7ef4\u7c7b", "secondType": "\u6d4b\u8bd5", "isSchoolJob": 0, "subwayline": null, "stationname": null, "linestaion": null, "thirdType": "\u81ea\u52a8\u5316\u6d4b\u8bd5", "skillLables": [], "longitude": "118.192317", "latitude": "24.475824", "formatCreateTime": "2\u5929\u524d\u53d1\u5e03"}]}}}